Workbook

Sheet Modelo
A1: Projeto Asia (China) - Modelo Financeiro do Headcount
A2: Celulas amarelas sao editaveis. Tudo recalcula automaticamente. Valores anuais em R$.
A4: PREMISSAS (editaveis)
A5: Pool Profit OFF a agentes (12m) | B5: 2040000
A6: Parcela "intelectual" capturavel do pool (%) | B6: 0.7 | C6: parte do pool que 1 pessoa consegue negociar (resto e transacional)
A7: Custo do headcount (salario + encargos) | B7: 600000
A8: Taxa de estrutura da RS (% sobre captura) | B8: 0.15 | C8: taxa que a RS cobra para hospedar o headcount (ponto em aberto)
A9: % de captura do pool capturavel (meta) | B9: 0.3 | C9: quanto do pool capturavel o profissional efetivamente traz
A11: RESULTADO (calculado)
A12: Pool capturavel (R$) | B12: =B5*B6
A13: Captura bruta (R$) | B13: =B12*B9
A14: Taxa paga a RS (R$) | B14: =B13*B8
A15: Captura liquida (R$) | B15: =B13-B14
A16: Resultado anual (liquida - custo) | B16: =B15-B7
A17: Cobertura do custo (liquida / custo) | B17: =B15/B7
A19: PONTO DE EQUILIBRIO
A20: % de captura p/ break-even (dada taxa RS atual) | B20: =B7/(B12*(1-B8)) | C20: abaixo disso o headcount da prejuizo no cenario de taxa RS informado
A21: Status do cenario atual | B21: =SE(B16>=0;"VIAVEL (resultado >= 0)";"ABAIXO DO BREAK-EVEN")

Sheet Sensibilidade
A1: Sensibilidade: Resultado anual (R$) por % de captura x taxa da RS
A2: Cada celula = captura liquida - custo. Verde = viavel (>=0), vermelho = prejuizo. Usa as premissas da aba Modelo (pool, parcela, custo).
A4: Captura \ Taxa RS | B4: 0 | C4: 0.05 | D4: 0.1 | E4: 0.15 | F4: 0.2 | G4: 0.25 | H4: 0.3
A5: 0.1 | B5: =Modelo!$B$12*$A5*(1-B$4)-Modelo!$B$7 | C5: =Modelo!$B$12*$A5*(1-C$4)-Modelo!$B$7 | D5: =Modelo!$B$12*$A5*(1-D$4)-Modelo!$B$7 | E5: =Modelo!$B$12*$A5*(1-E$4)-Modelo!$B$7 | F5: =Modelo!$B$12*$A5*(1-F$4)-Modelo!$B$7 | G5: =Modelo!$B$12*$A5*(1-G$4)-Modelo!$B$7 | H5: =Modelo!$B$12*$A5*(1-H$4)-Modelo!$B$7
A6: 0.15 | B6: =Modelo!$B$12*$A6*(1-B$4)-Modelo!$B$7 | C6: =Modelo!$B$12*$A6*(1-C$4)-Modelo!$B$7 | D6: =Modelo!$B$12*$A6*(1-D$4)-Modelo!$B$7 | E6: =Modelo!$B$12*$A6*(1-E$4)-Modelo!$B$7 | F6: =Modelo!$B$12*$A6*(1-F$4)-Modelo!$B$7 | G6: =Modelo!$B$12*$A6*(1-G$4)-Modelo!$B$7 | H6: =Modelo!$B$12*$A6*(1-H$4)-Modelo!$B$7
A7: 0.2 | B7: =Modelo!$B$12*$A7*(1-B$4)-Modelo!$B$7 | C7: =Modelo!$B$12*$A7*(1-C$4)-Modelo!$B$7 | D7: =Modelo!$B$12*$A7*(1-D$4)-Modelo!$B$7 | E7: =Modelo!$B$12*$A7*(1-E$4)-Modelo!$B$7 | F7: =Modelo!$B$12*$A7*(1-F$4)-Modelo!$B$7 | G7: =Modelo!$B$12*$A7*(1-G$4)-Modelo!$B$7 | H7: =Modelo!$B$12*$A7*(1-H$4)-Modelo!$B$7
A8: 0.25 | B8: =Modelo!$B$12*$A8*(1-B$4)-Modelo!$B$7 | C8: =Modelo!$B$12*$A8*(1-C$4)-Modelo!$B$7 | D8: =Modelo!$B$12*$A8*(1-D$4)-Modelo!$B$7 | E8: =Modelo!$B$12*$A8*(1-E$4)-Modelo!$B$7 | F8: =Modelo!$B$12*$A8*(1-F$4)-Modelo!$B$7 | G8: =Modelo!$B$12*$A8*(1-G$4)-Modelo!$B$7 | H8: =Modelo!$B$12*$A8*(1-H$4)-Modelo!$B$7
A9: 0.3 | B9: =Modelo!$B$12*$A9*(1-B$4)-Modelo!$B$7 | C9: =Modelo!$B$12*$A9*(1-C$4)-Modelo!$B$7 | D9: =Modelo!$B$12*$A9*(1-D$4)-Modelo!$B$7 | E9: =Modelo!$B$12*$A9*(1-E$4)-Modelo!$B$7 | F9: =Modelo!$B$12*$A9*(1-F$4)-Modelo!$B$7 | G9: =Modelo!$B$12*$A9*(1-G$4)-Modelo!$B$7 | H9: =Modelo!$B$12*$A9*(1-H$4)-Modelo!$B$7
A10: 0.35 | B10: =Modelo!$B$12*$A10*(1-B$4)-Modelo!$B$7 | C10: =Modelo!$B$12*$A10*(1-C$4)-Modelo!$B$7 | D10: =Modelo!$B$12*$A10*(1-D$4)-Modelo!$B$7 | E10: =Modelo!$B$12*$A10*(1-E$4)-Modelo!$B$7 | F10: =Modelo!$B$12*$A10*(1-F$4)-Modelo!$B$7 | G10: =Modelo!$B$12*$A10*(1-G$4)-Modelo!$B$7 | H10: =Modelo!$B$12*$A10*(1-H$4)-Modelo!$B$7
A11: 0.4 | B11: =Modelo!$B$12*$A11*(1-B$4)-Modelo!$B$7 | C11: =Modelo!$B$12*$A11*(1-C$4)-Modelo!$B$7 | D11: =Modelo!$B$12*$A11*(1-D$4)-Modelo!$B$7 | E11: =Modelo!$B$12*$A11*(1-E$4)-Modelo!$B$7 | F11: =Modelo!$B$12*$A11*(1-F$4)-Modelo!$B$7 | G11: =Modelo!$B$12*$A11*(1-G$4)-Modelo!$B$7 | H11: =Modelo!$B$12*$A11*(1-H$4)-Modelo!$B$7
A12: 0.5 | B12: =Modelo!$B$12*$A12*(1-B$4)-Modelo!$B$7 | C12: =Modelo!$B$12*$A12*(1-C$4)-Modelo!$B$7 | D12: =Modelo!$B$12*$A12*(1-D$4)-Modelo!$B$7 | E12: =Modelo!$B$12*$A12*(1-E$4)-Modelo!$B$7 | F12: =Modelo!$B$12*$A12*(1-F$4)-Modelo!$B$7 | G12: =Modelo!$B$12*$A12*(1-G$4)-Modelo!$B$7 | H12: =Modelo!$B$12*$A12*(1-H$4)-Modelo!$B$7
A13: 0.6 | B13: =Modelo!$B$12*$A13*(1-B$4)-Modelo!$B$7 | C13: =Modelo!$B$12*$A13*(1-C$4)-Modelo!$B$7 | D13: =Modelo!$B$12*$A13*(1-D$4)-Modelo!$B$7 | E13: =Modelo!$B$12*$A13*(1-E$4)-Modelo!$B$7 | F13: =Modelo!$B$12*$A13*(1-F$4)-Modelo!$B$7 | G13: =Modelo!$B$12*$A13*(1-G$4)-Modelo!$B$7 | H13: =Modelo!$B$12*$A13*(1-H$4)-Modelo!$B$7
A15: Leitura: o verde comeca por volta de 30% de captura; com a taxa da RS subindo, a fronteira do break-even desloca para a direita, exigindo capturar mais para o mesmo resultado.

Sheet Notas e Fontes
A1: MODELO FINANCEIRO - PROJETO ASIA (CHINA)
A3: Objetivo: testar a viabilidade do headcount local sensibilizando as duas variaveis em aberto:
A4: (1) a taxa de estrutura cobrada pela RS Logistics e (2) o % de captura que 1 pessoa consegue.
A6: Premissas e fontes:
A7: - Pool Profit OFF a agentes R$ 2,04 mi: apresentacao DMS +Asia (abr/25-mar/26), universo teorico.
A8: - Custo headcount R$ 550-650 mil (usado 600 mil de base): ERI SalaryExpert / Morgan McKinley 2025-26.
A9: - Parcela capturavel 70%: premissa de trabalho - parte do pool e transacional (doc/desembaraco),
A10: nao substituivel por 1 pessoa. AJUSTAR quando o cliente detalhar a composicao do pool.
A11: - Taxa da RS: NAO INFORMADA pelo cliente - e a principal variavel em aberto. Default 15% ilustrativo.
A12: - % captura meta 30%: coerente com o break-even citado no deck para custo ~600k sem taxa RS.
A14: Como usar:
A15: - Aba Modelo: mude as celulas amarelas; o resultado e o break-even recalculam.
... A22: - Nao inclui custo de transicao nem risco de perda de servico na migracao dos 2 agentes (69%).
